mcp_server_r_counter/__init__.py
mcp_server_r_counter/r_counter.py
mcp_server_r_counter-0.0.3.dist-info/METADATA
mcp_server_r_counter-0.0.3.dist-info/WHEEL
mcp_server_r_counter-0.0.3.dist-info/entry_points.txt
mcp_server_r_counter-0.0.3.dist-info/RECORD
