Metadata-Version: 2.4
Name: mcp-server-r-counter
Version: 0.0.3
Summary: A MCP Server Counting Number of r's for a Given Query
Requires-Dist: mcp>=1.4.1
